{
  "1": {
    "inputs": {
      "ckpt_name": "diffusers model"
    },
    "class_type": "CheckpointLoaderSimple"
  },
  "2": {
    "inputs": {
      "vae_name": "vae model"
    },
    "class_type": "VAELoader"
  },
  "4": {
    "inputs": {
      "text": "positive prompt",
      "clip": [
        "1",
        1
      ]
    },
    "class_type": "CLIPTextEncode"
  },
  "5": {
    "inputs": {
      "text": "negative prompt",
      "clip": [
        "1",
        1
      ]
    },
    "class_type": "CLIPTextEncode"
  },
  "6": {
    "inputs": {
      "image": "source image",
      "choose file to upload": "image"
    },
    "class_type": "LoadImage"
  },
  "11": {
    "inputs": {
      "add_noise": "enable",
      "noise_seed": 615368952465653,
      "steps": 30,
      "cfg": 8,
      "sampler_name": "uni_pc",
      "scheduler": "normal",
      "start_at_step": 0,
      "end_at_step": 10000,
      "return_with_leftover_noise": "disable",
      "model": [
        "1",
        0
      ],
      "positive": [
        "15",
        0
      ],
      "negative": [
        "5",
        0
      ],
      "latent_image": [
        "16",
        0
      ]
    },
    "class_type": "KSamplerAdvanced"
  },
  "12": {
    "inputs": {
      "samples": [
        "11",
        0
      ],
      "vae": [
        "2",
        0
      ]
    },
    "class_type": "VAEDecode"
  },
  "13": {
    "inputs": {
      "filename_prefix": "ComfyUI",
      "images": [
        "18",
        0
      ]
    },
    "class_type": "SaveImage"
  },
  "14": {
    "inputs": {
      "control_net_name": "controlnet model"
    },
    "class_type": "ControlNetLoader"
  },
  "15": {
    "inputs": {
      "strength": 1,
      "conditioning": [
        "4",
        0
      ],
      "control_net": [
        "14",
        0
      ],
      "image": [
        "6",
        0
      ]
    },
    "class_type": "ControlNetApply"
  },
  "16": {
    "inputs": {
      "width": 512,
      "height": 512,
      "batch_size": 1
    },
    "class_type": "EmptyLatentImage"
  },
  "18": {
    "inputs": {
      "upscale_model": [
        "19",
        0
      ],
      "image": [
        "12",
        0
      ]
    },
    "class_type": "ImageUpscaleWithModel"
  },
  "19": {
    "inputs": {
      "model_name": "8xNMKDFaces160000G_v10.pt"
    },
    "class_type": "UpscaleModelLoader"
  }
}
